plotski/__init__.py
plotski/_version.py
plotski/base.py
plotski/enums.py
plotski/image.py
plotski/rgb.py
plotski/scatter.py
plotski/utilities.py
plotski/spectrum/__init__.py
plotski/spectrum/custom.py
plotski/spectrum/plot.py
plotski/store/__init__.py
plotski/store/containers.py
plotski/store/custom.py
plotski-0.2.0.dist-info/AUTHORS.md
plotski-0.2.0.dist-info/LICENSE
plotski-0.2.0.dist-info/METADATA
plotski-0.2.0.dist-info/WHEEL
plotski-0.2.0.dist-info/top_level.txt
plotski-0.2.0.dist-info/RECORD
