Metadata-Version: 2.1
Name: plotski
Version: 0.2.0
Summary: Convenient interactive plotting in Python.
Author-email: "Lukasz G. Migas" <lukas.migas@yahoo.com>
License: BSD 3-Clause License
Project-URL: homepage, https://github.com/lukasz-migas/plotski
Project-URL: repository, https://github.com/lukasz-migas/plotski
Classifier: Development Status :: 3 - Alpha
Classifier: Intended Audience :: Education
Classifier: Intended Audience :: Science/Research
Classifier: License :: OSI Approved :: MIT License
Classifier: Natural Language :: English
Classifier: Programming Language :: Python
Classifier: Programming Language :: Python :: 3 :: Only
Classifier: Programming Language :: Python :: 3
Classifier: Programming Language :: Python :: 3.8
Classifier: Programming Language :: Python :: 3.9
Classifier: Programming Language :: Python :: 3.10
Classifier: Typing :: Typed
Classifier: Topic :: Scientific/Engineering :: Visualization
Classifier: Topic :: Utilities
Classifier: Operating System :: POSIX
Classifier: Operating System :: Unix
Classifier: Operating System :: MacOS
Requires-Python: >=3.8
License-File: LICENSE
License-File: AUTHORS.md
Requires-Dist: bokeh (>=3.0.0)
Requires-Dist: scikit-image (>=0.19.0)
Requires-Dist: matplotlib (>=3.3.0)
Requires-Dist: numpy (<=1.24,>=1.21) ; python_version < "3.10"
Requires-Dist: numpy (<=1.24,>=1.22) ; python_version >= "3.10"
Provides-Extra: dev
Requires-Dist: black (==22.1.0) ; extra == 'dev'
Requires-Dist: ipython ; extra == 'dev'
Requires-Dist: mypy ; extra == 'dev'
Requires-Dist: pdbpp ; extra == 'dev'
Requires-Dist: pre-commit ; extra == 'dev'
Requires-Dist: pytest ; extra == 'dev'
Requires-Dist: rich ; extra == 'dev'
Requires-Dist: ruff ; extra == 'dev'
Requires-Dist: koyo[test] ; extra == 'dev'
Provides-Extra: test
Requires-Dist: pytest (>=6.0) ; extra == 'test'
Requires-Dist: pytest-cov ; extra == 'test'
